blotch/__init__.py
blotch-0.0.0.dist-info/LICENSE
blotch-0.0.0.dist-info/METADATA
blotch-0.0.0.dist-info/WHEEL
blotch-0.0.0.dist-info/entry_points.txt
blotch-0.0.0.dist-info/top_level.txt
blotch-0.0.0.dist-info/RECORD
