Metadata-Version: 2.1
Name: blotch
Version: 0.0.0
Summary: Publication Quality Plotting Utilities for Machine Learning
Home-page: https://github.com/geyang/alice
Author: Ge Yang
Author-email: ge.ike.yang@gmail.com
License: UNKNOWN
Keywords: blotch,visualization,publication,plot
Platform: UNKNOWN
Classifier: Development Status :: 4 - Beta
Classifier: Intended Audience :: Science/Research
Classifier: Programming Language :: Python :: 3
